weather_mcp/__init__.py
weather_mcp/__main__.py
weather_mcp/_version.py
weather_mcp/main.py
weather_context_mcp-0.2.14.dist-info/METADATA
weather_context_mcp-0.2.14.dist-info/WHEEL
weather_context_mcp-0.2.14.dist-info/entry_points.txt
weather_context_mcp-0.2.14.dist-info/licenses/LICENSE
weather_context_mcp-0.2.14.dist-info/RECORD
