Metadata-Version: 2.4
Name: weather-context-mcp
Version: 0.2.14
Summary: An MCP for retrieving historical weather data for a given location
Project-URL: Homepage, https://github.com/contextualizer-ai/weather-mcp
Project-URL: Repository, https://github.com/contextualizer-ai/weather-mcp
Project-URL: Issues, https://github.com/contextualizer-ai/weather-mcp/issues
Project-URL: Documentation, https://github.com/contextualizer-ai/weather-mcp#readme
Author-email: Justin Reese <justaddcoffee@gmail.com>, Mark Andrew Miller <MAM@lbl.gov>, Charles Parker <ctparker@lbl.gov>
License: BSD3-LBNL
License-File: LICENSE
Keywords: geospatial,gis,mcp,nlcd,weather
Classifier: Development Status :: 4 - Beta
Classifier: Intended Audience :: Developers
Classifier: Intended Audience :: Science/Research
Classifier: License :: OSI Approved :: MIT License
Classifier: Operating System :: OS Independent
Classifier: Programming Language :: Python :: 3
Classifier: Programming Language :: Python :: 3.10
Classifier: Programming Language :: Python :: 3.11
Classifier: Programming Language :: Python :: 3.12
Classifier: Topic :: Scientific/Engineering :: GIS
Classifier: Topic :: Software Development :: Libraries :: Python Modules
Requires-Python: >=3.10
Requires-Dist: fastmcp>=2.7.1
Requires-Dist: meteostat>=1.7.4
Requires-Dist: pandas>=2.3.0
Requires-Dist: requests>=2.32.4
